Type_escocotheloco/Type.py
Type_escocotheloco/__init__.py
type_escocotheloco-0.0.1.dist-info/METADATA
type_escocotheloco-0.0.1.dist-info/WHEEL
type_escocotheloco-0.0.1.dist-info/licenses/LICENSE.txt
type_escocotheloco-0.0.1.dist-info/RECORD
